{"python": "def compound_4198(x, y):\n    return (jnp.tanh(jnp.exp(-jnp.abs(x)))) * ((y)**2)", "ir": "module @jit_compound_4198 attributes {mhlo.num_partitions = 1 : i32, mhlo.num_replicas = 1 : i32} {\n  func.func public @main(%arg0: tensor<6xf32>, %arg1: tensor<6xf32>) -> (tensor<6xf32> {jax.result_info = \"result\"}) {\n    %0 = stablehlo.abs %arg0 : tensor<6xf32>\n    %1 = stablehlo.negate %0 : tensor<6xf32>\n    %2 = stablehlo.exponential %1 : tensor<6xf32>\n    %3 = stablehlo.tanh %2 : tensor<6xf32>\n    %4 = stablehlo.multiply %arg1, %arg1 : tensor<6xf32>\n    %5 = stablehlo.multiply %3, %4 : tensor<6xf32>\n    return %5 : tensor<6xf32>\n  }\n}\n", "ir_format": "stablehlo", "function_type": "compound", "arg_shapes": [{"shape": [6], "dtype": "float32"}, {"shape": [6], "dtype": "float32"}]}