{
  "python_source": "@wp.kernel\ndef rand_expr_thqync(data: wp.array(dtype=float)):\n    tid = wp.tid()\n    v0 = data[tid]\n    v1 = 0.0\n    v2 = 1.0\n    tmp = 0.0\n    v2 = ((v1 * 0.16) - v1)\n    v1 = wp.cos(0.63)\n    v0 = (0.14 / wp.cos((v1 + 0.61 - tmp + 0.31)))\n    v0 = wp.abs((wp.cos(v1 + 0.28) + (tmp + 0.59 * v2 + 0.75)))\n    v0 = (wp.sin(0.75) + wp.cos((v0 + 0.98 * v1 + 0.76)))\n    tmp = wp.exp(0.07)\n    v2 = 0.98\n    v0 = v1\n    data[tid] = v0\n",
  "cpp_forward": "void rand_expr_thqync_51a134ff_cpu_kernel_forward(\n    wp::launch_bounds_t dim,\n    size_t task_index,\n    wp_args_rand_expr_thqync_51a134ff *_wp_args)\n{\n    //---------\n    // argument vars\n    wp::array_t<wp::float32> var_data = _wp_args->data;\n    //---------\n    // primal vars\n    wp::int32 var_0;\n    wp::float32* var_1;\n    wp::float32 var_2;\n    wp::float32 var_3;\n    const wp::float32 var_4 = 0.0;\n    const wp::float32 var_5 = 1.0;\n    const wp::float32 var_6 = 0.0;\n    const wp::float32 var_7 = 0.16;\n    wp::float32 var_8;\n    wp::float32 var_9;\n    const wp::float32 var_10 = 0.63;\n    wp::float32 var_11;\n    const wp::float32 var_12 = 0.14;\n    const wp::float32 var_13 = 0.61;\n    wp::float32 var_14;\n    wp::float32 var_15;\n    const wp::float32 var_16 = 0.31;\n    wp::float32 var_17;\n    wp::float32 var_18;\n    wp::float32 var_19;\n    const wp::float32 var_20 = 0.28;\n    wp::float32 var_21;\n    wp::float32 var_22;\n    const wp::float32 var_23 = 0.59;\n    wp::float32 var_24;\n    wp::float32 var_25;\n    const wp::float32 var_26 = 0.75;\n    wp::float32 var_27;\n    wp::float32 var_28;\n    wp::float32 var_29;\n    const wp::float32 var_30 = 0.75;\n    wp::float32 var_31;\n    const wp::float32 var_32 = 0.98;\n    wp::float32 var_33;\n    wp::float32 var_34;\n    const wp::float32 var_35 = 0.76;\n    wp::float32 var_36;\n    wp::float32 var_37;\n    wp::float32 var_38;\n    const wp::float32 var_39 = 0.07;\n    wp::float32 var_40;\n    const wp::float32 var_41 = 0.98;\n    wp::float32 var_42;\n    //---------\n    // forward\n    // def rand_expr_thqync(data: wp.array(dtype=float)):                                     <L 83>\n    // tid = wp.tid()                                                                         <L 84>\n    var_0 = builtin_tid1d();\n    // v0 = data[tid]                                                                         <L 85>\n    var_1 = wp::address(var_data, var_0);\n    var_3 = wp::load(var_1);\n    var_2 = wp::copy(var_3);\n    // v1 = 0.0                                                                               <L 86>\n    // v2 = 1.0                                                                               <L 87>\n    // tmp = 0.0                                                                              <L 88>\n    // v2 = ((v1 * 0.16) - v1)                                                                <L 89>\n    var_8 = wp::mul(var_4, var_7);\n    var_9 = wp::sub(var_8, var_4);\n    // v1 = wp.cos(0.63)                                                                      <L 90>\n    var_11 = wp::cos(var_10);\n    // v0 = (0.14 / wp.cos((v1 + 0.61 - tmp + 0.31)))                                         <L 91>\n    var_14 = wp::add(var_11, var_13);\n    var_15 = wp::sub(var_14, var_6);\n    var_17 = wp::add(var_15, var_16);\n    var_18 = wp::cos(var_17);\n    var_19 = wp::div(var_12, var_18);\n    // v0 = wp.abs((wp.cos(v1 + 0.28) + (tmp + 0.59 * v2 + 0.75)))                            <L 92>\n    var_21 = wp::add(var_11, var_20);\n    var_22 = wp::cos(var_21);\n    var_24 = wp::mul(var_23, var_9);\n    var_25 = wp::add(var_6, var_24);\n    var_27 = wp::add(var_25, var_26);\n    var_28 = wp::add(var_22, var_27);\n    var_29 = wp::abs(var_28);\n    // v0 = (wp.sin(0.75) + wp.cos((v0 + 0.98 * v1 + 0.76)))                                  <L 93>\n    var_31 = wp::sin(var_30);\n    var_33 = wp::mul(var_32, var_11);\n    var_34 = wp::add(var_29, var_33);\n    var_36 = wp::add(var_34, var_35);\n    var_37 = wp::cos(var_36);\n    var_38 = wp::add(var_31, var_37);\n    // tmp = wp.exp(0.07)                                                                     <L 94>\n    var_40 = wp::exp(var_39);\n    // v2 = 0.98                                                                              <L 95>\n    // v0 = v1                                                                                <L 96>\n    var_42 = wp::copy(var_11);\n    // data[tid] = v0                                                                         <L 97>\n    wp::array_store(var_data, var_0, var_42);\n}",
  "metadata": {
    "kernel_name": "rand_expr_thqync",
    "category": "random_math",
    "device": "cpu",
    "batch_id": 1651
  }
}