{
  "python_source": "@wp.kernel\ndef rand_expr_kibgie(data: wp.array(dtype=float)):\n    tid = wp.tid()\n    v0 = data[tid]\n    v1 = 0.0\n    v2 = 1.0\n    tmp = 0.0\n    v0 = (0.13 * v1)\n    v2 = wp.exp(((v1 + 0.74 / tmp + 0.65) / (v2 + 0.11 * v2 + 0.83)))\n    v1 = wp.exp((wp.abs(v2 + 0.86) * wp.cos(tmp + 0.09)))\n    v2 = (0.56 * 0.46)\n    tmp = wp.sin(wp.abs((tmp + 0.35 + v0 + 0.46)))\n    v2 = tmp\n    v2 = wp.sin(wp.abs(wp.sin(tmp + 0.97)))\n    v1 = 0.68\n    data[tid] = v0\n",
  "cpp_forward": "void rand_expr_kibgie_6cf1dbcc_cuda_kernel_forward(\n    wp::launch_bounds_t dim,\n    wp::array_t<wp::float32> var_data)\n{\n    wp::tile_shared_storage_t tile_mem;\n\n    for (size_t _idx = static_cast<size_t>(blockDim.x) * static_cast<size_t>(blockIdx.x) + static_cast<size_t>(threadIdx.x);\n         _idx < dim.size;\n         _idx += static_cast<size_t>(blockDim.x) * static_cast<size_t>(gridDim.x))\n    {\n            // reset shared memory allocator\n        wp::tile_shared_storage_t::init();\n\n        //---------\n        // primal vars\n        wp::int32 var_0;\n        wp::float32* var_1;\n        wp::float32 var_2;\n        wp::float32 var_3;\n        const wp::float32 var_4 = 0.0;\n        const wp::float32 var_5 = 1.0;\n        const wp::float32 var_6 = 0.0;\n        const wp::float32 var_7 = 0.13;\n        wp::float32 var_8;\n        const wp::float32 var_9 = 0.74;\n        wp::float32 var_10;\n        wp::float32 var_11;\n        const wp::float32 var_12 = 0.65;\n        wp::float32 var_13;\n        const wp::float32 var_14 = 0.11;\n        wp::float32 var_15;\n        wp::float32 var_16;\n        const wp::float32 var_17 = 0.83;\n        wp::float32 var_18;\n        wp::float32 var_19;\n        wp::float32 var_20;\n        const wp::float32 var_21 = 0.86;\n        wp::float32 var_22;\n        wp::float32 var_23;\n        const wp::float32 var_24 = 0.09;\n        wp::float32 var_25;\n        wp::float32 var_26;\n        wp::float32 var_27;\n        wp::float32 var_28;\n        const wp::float32 var_29 = 0.56;\n        const wp::float32 var_30 = 0.46;\n        wp::float32 var_31;\n        const wp::float32 var_32 = 0.35;\n        wp::float32 var_33;\n        wp::float32 var_34;\n        const wp::float32 var_35 = 0.46;\n        wp::float32 var_36;\n        wp::float32 var_37;\n        wp::float32 var_38;\n        wp::float32 var_39;\n        const wp::float32 var_40 = 0.97;\n        wp::float32 var_41;\n        wp::float32 var_42;\n        wp::float32 var_43;\n        wp::float32 var_44;\n        const wp::float32 var_45 = 0.68;\n        //---------\n        // forward\n        // def rand_expr_kibgie(data: wp.array(dtype=float)):                                     <L 4>\n        // tid = wp.tid()                                                                         <L 5>\n        var_0 = builtin_tid1d();\n        // v0 = data[tid]                                                                         <L 6>\n        var_1 = wp::address(var_data, var_0);\n        var_3 = wp::load(var_1);\n        var_2 = wp::copy(var_3);\n        // v1 = 0.0                                                                               <L 7>\n        // v2 = 1.0                                                                               <L 8>\n        // tmp = 0.0                                                                              <L 9>\n        // v0 = (0.13 * v1)                                                                       <L 10>\n        var_8 = wp::mul(var_7, var_4);\n        // v2 = wp.exp(((v1 + 0.74 / tmp + 0.65) / (v2 + 0.11 * v2 + 0.83)))                      <L 11>\n        var_10 = wp::div(var_9, var_6);\n        var_11 = wp::add(var_4, var_10);\n        var_13 = wp::add(var_11, var_12);\n        var_15 = wp::mul(var_14, var_5);\n        var_16 = wp::add(var_5, var_15);\n        var_18 = wp::add(var_16, var_17);\n        var_19 = wp::div(var_13, var_18);\n        var_20 = wp::exp(var_19);\n        // v1 = wp.exp((wp.abs(v2 + 0.86) * wp.cos(tmp + 0.09)))                                  <L 12>\n        var_22 = wp::add(var_20, var_21);\n        var_23 = wp::abs(var_22);\n        var_25 = wp::add(var_6, var_24);\n        var_26 = wp::cos(var_25);\n        var_27 = wp::mul(var_23, var_26);\n        var_28 = wp::exp(var_27);\n        // v2 = (0.56 * 0.46)                                                                     <L 13>\n        var_31 = wp::mul(var_29, var_30);\n        // tmp = wp.sin(wp.abs((tmp + 0.35 + v0 + 0.46)))                                         <L 14>\n        var_33 = wp::add(var_6, var_32);\n        var_34 = wp::add(var_33, var_8);\n        var_36 = wp::add(var_34, var_35);\n        var_37 = wp::abs(var_36);\n        var_38 = wp::sin(var_37);\n        // v2 = tmp                                                                               <L 15>\n        var_39 = wp::copy(var_38);\n        // v2 = wp.sin(wp.abs(wp.sin(tmp + 0.97)))                                                <L 16>\n        var_41 = wp::add(var_38, var_40);\n        var_42 = wp::sin(var_41);\n        var_43 = wp::abs(var_42);\n        var_44 = wp::sin(var_43);\n        // v1 = 0.68                                                                              <L 17>\n        // data[tid] = v0                                                                         <L 18>\n        wp::array_store(var_data, var_0, var_8);\n    }\n}",
  "metadata": {
    "kernel_name": "rand_expr_kibgie",
    "category": "random_math",
    "device": "cuda"
  }
}