{
  "python_code": "@wp.kernel\ndef kernel_144(x: wp.array(dtype=float), result: wp.array(dtype=float), freq: float):\n    tid = wp.tid()\n    val = x[tid]\n    result[tid] = wp.cos(val * freq)\n",
  "ir_code": "void kernel_144_935a657b_cpu_kernel_forward(\n    wp::launch_bounds_t dim,\n    size_t task_index,\n    wp_args_kernel_144_935a657b *_wp_args)\n{\n    //---------\n    // argument vars\n    wp::array_t<wp::float32> var_x = _wp_args->x;\n    wp::array_t<wp::float32> var_result = _wp_args->result;\n    wp::float32 var_freq = _wp_args->freq;\n    //---------\n    // primal vars\n    wp::int32 var_0;\n    wp::float32* var_1;\n    wp::float32 var_2;\n    wp::float32 var_3;\n    wp::float32 var_4;\n    wp::float32 var_5;\n    wp::float32 var_6;\n    const wp::float32 var_7 = 2.0;\n    wp::float32 var_8;\n    wp::float32 var_9;\n    wp::float32 var_10;\n    //---------\n    // forward\n    // def kernel_144(x: wp.array(dtype=float), result: wp.array(dtype=float), freq: float):       <L 4>\n    // tid = wp.tid()                                                                         <L 5>\n    var_0 = builtin_tid1d();\n    // val = x[tid]                                                                           <L 6>\n    var_1 = wp::address(var_x, var_0);\n    var_3 = wp::load(var_1);\n    var_2 = wp::copy(var_3);\n    // result[tid] = wp.sin(val * freq) * wp.cos(val * freq * 2.0)                            <L 7>\n    var_4 = wp::mul(var_2, var_freq);\n    var_5 = wp::sin(var_4);\n    var_6 = wp::mul(var_2, var_freq);\n    var_8 = wp::mul(var_6, var_7);\n    var_9 = wp::cos(var_8);\n    var_10 = wp::mul(var_5, var_9);\n    wp::array_store(var_result, var_0, var_10);\n}",
  "metadata": {
    "kernel_name": "kernel_144",
    "op_type": "trigonometry",
    "complexity": 1,
    "num_inputs": 1,
    "num_outputs": 1,
    "has_scalar_param": true,
    "python_lines": 6,
    "ir_lines": 41
  }
}